d1snake/__init__.py
d1snake/__main__.py
d1snake/game.py
d1snakegame-0.1.2.dist-info/METADATA
d1snakegame-0.1.2.dist-info/WHEEL
d1snakegame-0.1.2.dist-info/entry_points.txt
d1snakegame-0.1.2.dist-info/top_level.txt
d1snakegame-0.1.2.dist-info/RECORD
