Metadata-Version: 2.4
Name: d1snakegame
Version: 0.1.2
Summary: A simple snake game in Python using pygame
Author: Drifys1
Requires-Dist: pygame
